<manifest alg="2" build="2018.1.0.386" opt="false" iceEnabled="true" iceMarkupVersion="2" iceEnabledOptions="link,responsive,cachebuster,textStyling" exportTarget="other" domain="appries.com" resolutions="1x" timestamp="1537465711891">
  <folder name="assets">
    <file name="ezgif.com-optimize.gif" crc="4016622575" seo="true" mt="1533248845000"/>
    <file name="2.gif" crc="3872288782" seo="true" mt="1533290408000"/>
  </folder>
  <folder name="css">
    <file name="site_global.css" crc="219438036"/>
    <file name="master_a-master.css" crc="354096969" ref="index:class-arena:360:live:vr:news:e-store:library:appries-talk:untitled-7:untitled-5:motivation:user:contact:info:roll-model:untitled-6"/>
    <file name="index.css" crc="4253111700" ref="index"/>
    <file name="master_c-master.css" crc="442082512" ref="live:untitled-7:untitled-5:untitled-6"/>
    <file name="master_b-master.css" crc="3890970699" ref="class-arena:360:live:vr:news:e-store:library:appries-talk:untitled-7:untitled-5:motivation:user:contact:info:index:roll-model:untitled-6"/>
    <file name="class-arena.css" crc="4141890894" ref="class-arena"/>
    <file name="360.css" crc="72041905" ref="360"/>
    <file name="live.css" crc="416858500" ref="live"/>
    <file name="vr.css" crc="4167134868" ref="vr"/>
    <file name="news.css" crc="38985023" ref="news"/>
    <file name="e-store.css" crc="3765916525" ref="e-store"/>
    <file name="library.css" crc="456631345" ref="library"/>
    <file name="appries-talk.css" crc="3902626425" ref="appries-talk"/>
    <file name="untitled-7.css" crc="423930342" ref="untitled-7"/>
    <file name="untitled-5.css" crc="3967741812" ref="untitled-5"/>
    <file name="motivation.css" crc="4025855480" ref="motivation"/>
    <file name="user.css" crc="3788955641" ref="user"/>
    <file name="contact.css" crc="3788955641" ref="contact"/>
    <file name="info.css" crc="246653871" ref="info"/>
    <file name="roll-model.css" crc="3978519913" ref="roll-model"/>
    <file name="untitled-6.css" crc="4120853344" ref="untitled-6"/>
  </folder>
  <folder name="scripts">
    <file name="jquery-1.8.3.min.js" crc="209076791" ref="index:class-arena:live:360:untitled-5:untitled-6:untitled-7:library:e-store:user:info:motivation:vr:roll-model:appries-talk:news:contact"/>
    <file name="museutils.js" crc="340535759" ref="index:class-arena:live:360:untitled-5:untitled-6:untitled-7:library:e-store:user:info:motivation:vr:roll-model:appries-talk:news:contact"/>
    <file name="whatinput.js" crc="86476730" ref="index:class-arena:live:360:untitled-5:untitled-6:untitled-7:library:e-store:user:info:motivation:vr:roll-model:appries-talk:news:contact"/>
    <file name="museconfig.js" crc="4286661555" ref="index:class-arena:live:360:untitled-5:untitled-6:untitled-7:library:e-store:user:info:motivation:vr:roll-model:appries-talk:news:contact"/>
    <file name="jquery.watch.js" crc="51536988" ref="index:class-arena:live:360:untitled-5:untitled-6:untitled-7:library:e-store:user:info:motivation:vr:roll-model:appries-talk:news:contact"/>
    <file name="require.js" crc="7928878" ref="index:class-arena:live:360:untitled-5:untitled-6:untitled-7:library:e-store:user:info:motivation:vr:roll-model:appries-talk:news:contact"/>
    <file name="webpro.js" crc="4059564322" ref="class-arena:untitled-5:library:e-store:motivation:vr:appries-talk:news"/>
    <file name="jquery.musepolyfill.bgsize.js" crc="4260645839" ref="live:untitled-5:untitled-6:untitled-7"/>
    <file name="jquery.musemenu.js" crc="510910590" ref="index"/>
    <file name="html5shiv.js" crc="4241844378" ref="class-arena:live:360:untitled-5:untitled-6:untitled-7:library:user:info:motivation:vr:roll-model:appries-talk:news:contact:index"/>
    <file name="musewpdisclosure.js" crc="3883500470" ref="class-arena:untitled-5:library:e-store:motivation:vr:appries-talk:news"/>
  </folder>
  <folder name="images">
    <file name="blank.gif" crc="4208392903" ref="class-arena:untitled-5:library:e-store:motivation:vr:appries-talk:news:index"/>
    <file name="ic_home_white_24dp_2x.png" crc="216099558" seo="true" ref="index:class-arena:live:360:untitled-5:untitled-6:untitled-7:library:e-store:user:info:motivation:vr:roll-model:appries-talk:news:contact">
      <caption webpage="360" alt=""/>
      <caption webpage="appries-talk" alt=""/>
      <caption webpage="user" alt=""/>
      <caption webpage="e-store" alt=""/>
      <caption webpage="vr" alt=""/>
      <caption webpage="index" alt=""/>
      <caption webpage="library" alt=""/>
      <caption webpage="roll-model" alt=""/>
      <caption webpage="home" alt=""/>
      <caption webpage="info" alt=""/>
      <caption webpage="untitled-6" alt=""/>
      <caption webpage="news" alt=""/>
      <caption webpage="class-arena" alt=""/>
      <caption webpage="live" alt=""/>
      <caption webpage="untitled-7" alt=""/>
      <caption webpage="contact" alt=""/>
      <caption webpage="motivation" alt=""/>
      <caption webpage="untitled-5" alt=""/>
    </file>
    <file name="ic_class_white_24dp_2x.png" crc="3953811801" seo="true" ref="index:class-arena:live:360:untitled-5:untitled-6:untitled-7:library:e-store:user:info:motivation:vr:roll-model:appries-talk:news:contact">
      <caption webpage="360" alt=""/>
      <caption webpage="appries-talk" alt=""/>
      <caption webpage="user" alt=""/>
      <caption webpage="e-store" alt=""/>
      <caption webpage="vr" alt=""/>
      <caption webpage="index" alt=""/>
      <caption webpage="library" alt=""/>
      <caption webpage="roll-model" alt=""/>
      <caption webpage="home" alt=""/>
      <caption webpage="info" alt=""/>
      <caption webpage="untitled-6" alt=""/>
      <caption webpage="news" alt=""/>
      <caption webpage="class-arena" alt=""/>
      <caption webpage="live" alt=""/>
      <caption webpage="untitled-7" alt=""/>
      <caption webpage="contact" alt=""/>
      <caption webpage="motivation" alt=""/>
      <caption webpage="untitled-5" alt=""/>
    </file>
    <file name="folded-newspaper (1).png" crc="354703472" seo="true" ref="index:class-arena:live:360:untitled-5:untitled-6:untitled-7:library:e-store:user:info:motivation:vr:roll-model:appries-talk:news:contact">
      <caption webpage="360" alt=""/>
      <caption webpage="appries-talk" alt=""/>
      <caption webpage="user" alt=""/>
      <caption webpage="e-store" alt=""/>
      <caption webpage="vr" alt=""/>
      <caption webpage="index" alt=""/>
      <caption webpage="library" alt=""/>
      <caption webpage="roll-model" alt=""/>
      <caption webpage="home" alt=""/>
      <caption webpage="info" alt=""/>
      <caption webpage="untitled-6" alt=""/>
      <caption webpage="news" alt=""/>
      <caption webpage="class-arena" alt=""/>
      <caption webpage="live" alt=""/>
      <caption webpage="untitled-7" alt=""/>
      <caption webpage="contact" alt=""/>
      <caption webpage="motivation" alt=""/>
      <caption webpage="untitled-5" alt=""/>
    </file>
    <file name="table-clock.png" crc="15504003" seo="true" ref="index:class-arena:live:360:untitled-5:untitled-6:untitled-7:library:e-store:user:info:motivation:vr:roll-model:appries-talk:news:contact">
      <caption webpage="360" alt=""/>
      <caption webpage="appries-talk" alt=""/>
      <caption webpage="user" alt=""/>
      <caption webpage="e-store" alt=""/>
      <caption webpage="vr" alt=""/>
      <caption webpage="index" alt=""/>
      <caption webpage="library" alt=""/>
      <caption webpage="roll-model" alt=""/>
      <caption webpage="home" alt=""/>
      <caption webpage="info" alt=""/>
      <caption webpage="untitled-6" alt=""/>
      <caption webpage="news" alt=""/>
      <caption webpage="class-arena" alt=""/>
      <caption webpage="live" alt=""/>
      <caption webpage="untitled-7" alt=""/>
      <caption webpage="contact" alt=""/>
      <caption webpage="motivation" alt=""/>
      <caption webpage="untitled-5" alt=""/>
    </file>
    <file name="college-graduation.png" crc="4159836101" seo="true" ref="index:class-arena:live:360:untitled-5:untitled-6:untitled-7:library:e-store:user:info:motivation:vr:roll-model:appries-talk:news:contact">
      <caption webpage="360" alt=""/>
      <caption webpage="appries-talk" alt=""/>
      <caption webpage="user" alt=""/>
      <caption webpage="e-store" alt=""/>
      <caption webpage="vr" alt=""/>
      <caption webpage="index" alt=""/>
      <caption webpage="library" alt=""/>
      <caption webpage="roll-model" alt=""/>
      <caption webpage="home" alt=""/>
      <caption webpage="info" alt=""/>
      <caption webpage="untitled-6" alt=""/>
      <caption webpage="news" alt=""/>
      <caption webpage="class-arena" alt=""/>
      <caption webpage="live" alt=""/>
      <caption webpage="untitled-7" alt=""/>
      <caption webpage="contact" alt=""/>
      <caption webpage="motivation" alt=""/>
      <caption webpage="untitled-5" alt=""/>
    </file>
    <file name="feedback.png" crc="321401819" seo="true" ref="index:class-arena:live:360:untitled-5:untitled-6:untitled-7:library:e-store:user:info:motivation:vr:roll-model:appries-talk:news:contact">
      <caption webpage="360" alt=""/>
      <caption webpage="appries-talk" alt=""/>
      <caption webpage="user" alt=""/>
      <caption webpage="e-store" alt=""/>
      <caption webpage="vr" alt=""/>
      <caption webpage="index" alt=""/>
      <caption webpage="library" alt=""/>
      <caption webpage="roll-model" alt=""/>
      <caption webpage="home" alt=""/>
      <caption webpage="info" alt=""/>
      <caption webpage="untitled-6" alt=""/>
      <caption webpage="news" alt=""/>
      <caption webpage="class-arena" alt=""/>
      <caption webpage="live" alt=""/>
      <caption webpage="untitled-7" alt=""/>
      <caption webpage="contact" alt=""/>
      <caption webpage="motivation" alt=""/>
      <caption webpage="untitled-5" alt=""/>
    </file>
    <file name="gallery.png" crc="4137936359" seo="true" ref="index:class-arena:live:360:untitled-5:untitled-6:untitled-7:library:e-store:user:info:motivation:vr:roll-model:appries-talk:news:contact">
      <caption webpage="360" alt=""/>
      <caption webpage="appries-talk" alt=""/>
      <caption webpage="user" alt=""/>
      <caption webpage="e-store" alt=""/>
      <caption webpage="vr" alt=""/>
      <caption webpage="index" alt=""/>
      <caption webpage="library" alt=""/>
      <caption webpage="roll-model" alt=""/>
      <caption webpage="home" alt=""/>
      <caption webpage="info" alt=""/>
      <caption webpage="untitled-6" alt=""/>
      <caption webpage="news" alt=""/>
      <caption webpage="class-arena" alt=""/>
      <caption webpage="live" alt=""/>
      <caption webpage="untitled-7" alt=""/>
      <caption webpage="contact" alt=""/>
      <caption webpage="motivation" alt=""/>
      <caption webpage="untitled-5" alt=""/>
    </file>
    <file name="agenda.png" crc="3940889591" seo="true" ref="index:class-arena:live:360:untitled-5:untitled-6:untitled-7:library:e-store:user:info:motivation:vr:roll-model:appries-talk:news:contact">
      <caption webpage="360" alt=""/>
      <caption webpage="appries-talk" alt=""/>
      <caption webpage="user" alt=""/>
      <caption webpage="e-store" alt=""/>
      <caption webpage="vr" alt=""/>
      <caption webpage="index" alt=""/>
      <caption webpage="library" alt=""/>
      <caption webpage="roll-model" alt=""/>
      <caption webpage="home" alt=""/>
      <caption webpage="info" alt=""/>
      <caption webpage="untitled-6" alt=""/>
      <caption webpage="news" alt=""/>
      <caption webpage="class-arena" alt=""/>
      <caption webpage="live" alt=""/>
      <caption webpage="untitled-7" alt=""/>
      <caption webpage="contact" alt=""/>
      <caption webpage="motivation" alt=""/>
      <caption webpage="untitled-5" alt=""/>
    </file>
    <file name="evaluation.png" crc="493922299" seo="true" ref="index:class-arena:live:360:untitled-5:untitled-6:untitled-7:library:e-store:user:info:motivation:vr:roll-model:appries-talk:news:contact">
      <caption webpage="360" alt=""/>
      <caption webpage="appries-talk" alt=""/>
      <caption webpage="user" alt=""/>
      <caption webpage="e-store" alt=""/>
      <caption webpage="vr" alt=""/>
      <caption webpage="index" alt=""/>
      <caption webpage="library" alt=""/>
      <caption webpage="roll-model" alt=""/>
      <caption webpage="home" alt=""/>
      <caption webpage="info" alt=""/>
      <caption webpage="untitled-6" alt=""/>
      <caption webpage="news" alt=""/>
      <caption webpage="class-arena" alt=""/>
      <caption webpage="live" alt=""/>
      <caption webpage="untitled-7" alt=""/>
      <caption webpage="contact" alt=""/>
      <caption webpage="motivation" alt=""/>
      <caption webpage="untitled-5" alt=""/>
    </file>
    <file name="exam.png" crc="4086142318" seo="true" ref="index:class-arena:live:360:untitled-5:untitled-6:untitled-7:library:e-store:user:info:motivation:vr:roll-model:appries-talk:news:contact">
      <caption webpage="360" alt=""/>
      <caption webpage="appries-talk" alt=""/>
      <caption webpage="user" alt=""/>
      <caption webpage="e-store" alt=""/>
      <caption webpage="vr" alt=""/>
      <caption webpage="index" alt=""/>
      <caption webpage="library" alt=""/>
      <caption webpage="roll-model" alt=""/>
      <caption webpage="home" alt=""/>
      <caption webpage="info" alt=""/>
      <caption webpage="untitled-6" alt=""/>
      <caption webpage="news" alt=""/>
      <caption webpage="class-arena" alt=""/>
      <caption webpage="live" alt=""/>
      <caption webpage="untitled-7" alt=""/>
      <caption webpage="contact" alt=""/>
      <caption webpage="motivation" alt=""/>
      <caption webpage="untitled-5" alt=""/>
    </file>
    <file name="blackboard.png" crc="3903745103" seo="true" ref="class-arena">
      <caption webpage="class-arena" alt=""/>
    </file>
    <file name="ezgifcom-optimize.gif" crc="4239198289" seo="true" ref="class-arena">
      <caption webpage="class-arena" alt=""/>
    </file>
    <file name="live.gif" crc="731979" seo="true" ref="live:untitled-5:untitled-6:untitled-7">
      <caption webpage="live" alt=""/>
      <caption webpage="untitled-6" alt=""/>
      <caption webpage="untitled-7" alt=""/>
      <caption webpage="untitled-5" alt=""/>
    </file>
    <file name="live-online.gif" crc="4173961902" seo="true" ref="live">
      <caption webpage="live" alt=""/>
    </file>
    <file name="u1656-5.png" crc="174070069" ref="live"/>
    <file name="new(1).jpg" crc="4169499292" ref="live:untitled-5:untitled-6:untitled-7">
      <caption webpage="live" alt=""/>
      <caption webpage="untitled-6" alt=""/>
      <caption webpage="untitled-7" alt=""/>
      <caption webpage="untitled-5" alt=""/>
    </file>
    <file name="360-degrees.png" crc="4047945759" seo="true" ref="360">
      <caption webpage="360" alt=""/>
    </file>
    <file name="u1827.png" crc="294599544" ref="untitled-5"/>
    <file name="u1827-a.png" crc="3789201891" ref="untitled-5"/>
    <file name="u1873-5.png" crc="176314709" ref="untitled-7"/>
    <file name="wk2-min.png" crc="4058114455" seo="true" ref="e-store">
      <caption webpage="e-store" alt=""/>
    </file>
    <file name="wk3-min.png" crc="3927965858" seo="true" ref="e-store">
      <caption webpage="e-store" alt=""/>
    </file>
    <file name="wk1-min.png" crc="4090174943" seo="true" ref="e-store">
      <caption webpage="e-store" alt=""/>
    </file>
    <file name="a-logo.png" crc="355027145" seo="true" ref="info:motivation:vr:roll-model:news">
      <caption webpage="vr" alt=""/>
      <caption webpage="info" alt=""/>
      <caption webpage="motivation" alt=""/>
      <caption webpage="news" alt=""/>
      <caption webpage="roll-model" alt=""/>
    </file>
    <file name="u4189.png" crc="3973621778" ref="vr"/>
    <file name="u4189-a.png" crc="303186138" ref="vr"/>
    <file name="ezgifcom-resize(1).png" crc="3997572877" seo="true" ref="appries-talk">
      <caption webpage="appries-talk" alt=""/>
    </file>
    <file name="u4467.png" crc="324711241" ref="appries-talk"/>
    <file name="u4467-a.png" crc="324711241" ref="appries-talk"/>
  </folder>
  <file name="index.html" crc="3854474525" seo="true" mt="1536544775624" redirect="true"/>
  <file name="class-arena.html" crc="383674199" seo="true" mt="1536544775624" redirect="true"/>
  <file name="live.html" crc="3798794387" seo="true" mt="1537464422298" redirect="true"/>
  <file name="360.html" crc="4092229204" seo="true" mt="1537409773429" redirect="true"/>
  <file name="untitled-5.html" crc="273207339" seo="true" mt="1536544775624" redirect="true"/>
  <file name="untitled-6.html" crc="3853712195" seo="true" mt="1536544775624" redirect="true"/>
  <file name="untitled-7.html" crc="3758644076" seo="true" mt="1536544775624" redirect="true"/>
  <file name="library.html" crc="3970392095" seo="true" mt="1536544775624" redirect="true"/>
  <file name="e-store.html" crc="390855507" seo="true" mt="1537465648857" redirect="true"/>
  <file name="user.html" crc="317207951" seo="true" mt="1536544775624" redirect="true"/>
  <file name="info.html" crc="424111374" seo="true" mt="1536544775624" redirect="true"/>
  <file name="motivation.html" crc="310416865" seo="true" mt="1536544775624" redirect="true"/>
  <file name="vr.html" crc="3804129567" seo="true" mt="1536544775624" redirect="true"/>
  <file name="roll-model.html" crc="4122314566" seo="true" mt="1536544775624" redirect="true"/>
  <file name="appries-talk.html" crc="302468562" seo="true" mt="1536544775624" redirect="true"/>
  <file name="news.html" crc="371612298" seo="true" mt="1536544775624" redirect="true"/>
  <file name="contact.html" crc="19040206" seo="true" mt="1536544775624" redirect="true"/>
</manifest>